{
    "fluentMethods": true,
    "clientRootFolder": "carsapp",
    "relationships": [],
    "fields": [
        {
            "fieldName": "fabricante",
            "fieldType": "String",
            "fieldValidateRules": [
                "required"
            ]
        },
        {
            "fieldName": "modelo",
            "fieldType": "String",
            "fieldValidateRules": [
                "required"
            ]
        },
        {
            "fieldName": "precio",
            "fieldType": "BigDecimal",
            "fieldValidateRules": [
                "required",
                "min"
            ],
            "fieldValidateRulesMin": "0"
        }
    ],
    "changelogDate": "20190104155142",
    "dto": "no",
    "searchEngine": false,
    "service": "serviceImpl",
    "entityTableName": "car",
    "jpaMetamodelFiltering": false,
    "pagination": "pagination",
    "microserviceName": "carsapp"
}
